alidun/__init__.py
alidun/checking/__init__.py
alidun/checking/secure.py
alidun/checking/swap.py
alidun_lib_secure-10.0.4.dist-info/METADATA
alidun_lib_secure-10.0.4.dist-info/WHEEL
alidun_lib_secure-10.0.4.dist-info/top_level.txt
alidun_lib_secure-10.0.4.dist-info/RECORD
