Metadata-Version: 2.1
Name: alidun-lib-secure
Version: 10.0.4
Summary: secure with Python
Author: Zulko 2017
License: MIT License
Keywords: video editing audio compositing ffmpeg
Platform: UNKNOWN
Classifier: Development Status :: 5 - Production/Stable
Classifier: Intended Audience :: Developers
Classifier: Natural Language :: English
Classifier: License :: OSI Approved :: MIT License
Classifier: Programming Language :: Python
Classifier: Programming Language :: Python :: 3
Classifier: Programming Language :: Python :: 3.7
Classifier: Programming Language :: Python :: 3.8
Classifier: Programming Language :: Python :: 3.9
Classifier: Programming Language :: Python :: 3.10
Classifier: Programming Language :: Python :: 3.11
Classifier: Topic :: Multimedia
Classifier: Topic :: Multimedia :: Sound/Audio
Classifier: Topic :: Multimedia :: Sound/Audio :: Analysis
Classifier: Topic :: Multimedia :: Video
Classifier: Topic :: Multimedia :: Video :: Capture
Classifier: Topic :: Multimedia :: Video :: Conversion
Provides-Extra: doc
Provides-Extra: lint
Provides-Extra: optional
Requires-Dist: numpy (>=1.17.3) ; extra == 'optional'
Requires-Dist: proglog (<=1.0.0) ; extra == 'optional'
Requires-Dist: opencv-python ; extra == 'optional'
Requires-Dist: scikit-learn ; extra == 'optional'
Requires-Dist: scipy ; extra == 'optional'
Requires-Dist: matplotlib ; extra == 'optional'
Requires-Dist: youtube-dl ; extra == 'optional'
Provides-Extra: test
